longfor_test001-2.0.0.data/data/my_data/data_file
sample/__init__.py
sample/simple.py
longfor_test001-2.0.0.dist-info/LICENSE.txt
longfor_test001-2.0.0.dist-info/METADATA
longfor_test001-2.0.0.dist-info/WHEEL
longfor_test001-2.0.0.dist-info/top_level.txt
longfor_test001-2.0.0.dist-info/RECORD
