Metadata-Version: 2.1
Name: longfor-test001
Version: 2.0.0
Summary: A test project
Home-page: UNKNOWN
Author: A. Random Developer
Author-email: author@example.com
License: UNKNOWN
Keywords: sample,setuptools,development
Platform: UNKNOWN
Classifier: Development Status :: 3 - Alpha
Classifier: Intended Audience :: Developers
Classifier: Topic :: Software Development :: Build Tools
Classifier: License :: OSI Approved :: MIT License
Classifier: Programming Language :: Python :: 3
Classifier: Programming Language :: Python :: 3.7
Classifier: Programming Language :: Python :: 3.8
Classifier: Programming Language :: Python :: 3.9
Classifier: Programming Language :: Python :: 3.10
Classifier: Programming Language :: Python :: 3 :: Only
Requires-Python: >=3.7, <4
